README.txt
setup.py
lpdistutils/__init__.py
lpdistutils/bzrtag.py
lpdistutils/lpregister.py
lpdistutils/lpupload.py
lpdistutils.egg-info/PKG-INFO
lpdistutils.egg-info/SOURCES.txt
lpdistutils.egg-info/dependency_links.txt
lpdistutils.egg-info/requires.txt
lpdistutils.egg-info/top_level.txt
lpdistutils/tests/__init__.py
lpdistutils/tests/test_lpinfo.py
lpdistutils/tests/test_register.py