Metadata-Version: 1.0
Name: lpdistutils
Version: 0.1
Summary: Distutils commands for working with Launchpad and Bazaar.
Home-page: https://launchpad.net/lpdistutils
Author: James Westby
Author-email: james.westby@linaro.org
License: GPL2+
Platform: UNKNOWN
Classifier: Development Status :: 3 - Alpha
Classifier: Environment :: Plugins
Classifier: Framework :: Setuptools Plugin
Classifier: Intended Audience :: Developers
Classifier: License :: OSI Approved :: GNU General Public License (GPL)
Classifier: Programming Language :: Python
Classifier: Topic :: Software Development :: Build Tools
Classifier: Topic :: Software Development :: Version Control
